{
  "collectionName": "components_shared_heroes",
  "info": {
    "displayName": "Hero",
    "icon": "grid"
  },
  "options": {},
  "attributes": {
    "title": {
      "type": "string"
    },
    "subtitle": {
      "type": "string"
    },
    "backgroundImage": {
      "type": "media",
      "multiple": false,
      "allowedTypes": [
        "images",
        "files",
        "videos",
        "audios"
      ]
    },
    "buttonText": {
      "type": "string"
    },
    "buttonLink": {
      "type": "string"
    }
  },
  "config": {}
}
